vivialconnect/__init__.py
vivialconnect/version.py
vivialconnect/common/__init__.py
vivialconnect/common/error.py
vivialconnect/common/fields.py
vivialconnect/common/requestor.py
vivialconnect/common/util.py
vivialconnect/resources/__init__.py
vivialconnect/resources/account.py
vivialconnect/resources/connector.py
vivialconnect/resources/countable.py
vivialconnect/resources/log.py
vivialconnect/resources/message.py
vivialconnect/resources/number.py
vivialconnect/resources/resource.py
vivialconnect/resources/user.py
vivialconnect-0.2.4.dist-info/LICENSE
vivialconnect-0.2.4.dist-info/METADATA
vivialconnect-0.2.4.dist-info/WHEEL
vivialconnect-0.2.4.dist-info/top_level.txt
vivialconnect-0.2.4.dist-info/RECORD
