Metadata-Version: 2.1
Name: vivialconnect
Version: 0.2.4
Summary: Vivial Connect API Client Library for Python
Home-page: https://www.vivialconnect.net/
Author: Vivial Connect
Author-email: support@support.vivialconnect.net
License: MIT
Keywords: vivial,vivialconnect
Platform: any
Classifier: Intended Audience :: Developers
Classifier: License :: OSI Approved :: MIT License
Classifier: Operating System :: OS Independent
Classifier: Programming Language :: Python
Classifier: Programming Language :: Python :: 2.7
Classifier: Programming Language :: Python :: 3.2
Classifier: Programming Language :: Python :: 3.3
Classifier: Programming Language :: Python :: 3.4
Classifier: Programming Language :: Python :: 3.5
Classifier: Programming Language :: Python :: 3.6
Classifier: Programming Language :: Python :: 3.7
Classifier: Programming Language :: Python :: 3.8
Classifier: Topic :: Communications :: Telephony
Classifier: Topic :: Software Development :: Libraries :: Python Modules
Requires-Dist: requests (>=1.0.0)
Requires-Dist: six
